noconf/__init__.py
noconf/conf.py
noconf/test_conf.py
noconf-0.1a3.dist-info/METADATA
noconf-0.1a3.dist-info/WHEEL
noconf-0.1a3.dist-info/top_level.txt
noconf-0.1a3.dist-info/RECORD
