Metadata-Version: 2.1
Name: noconf
Version: 0.1a3
Summary: Component-based configuration for everyone!
Classifier: Programming Language :: Python :: 3
Provides-Extra: devel
Requires-Dist: pytest ; extra == 'devel'
Requires-Dist: ruff ; extra == 'devel'
